learnkeyhole/__init__.py
learnkeyhole/__main__.py
learnkeyhole/miou.py
learnkeyhole/predict.py
learnkeyhole/summary.py
learnkeyhole/train.py
learnkeyhole/unet.py
learnkeyhole/window.ui
learnkeyhole/nets/__init__.py
learnkeyhole/nets/resnet.py
learnkeyhole/nets/unet.py
learnkeyhole/nets/unet_training.py
learnkeyhole/nets/vgg.py
learnkeyhole/utils/__init__.py
learnkeyhole/utils/callbacks.py
learnkeyhole/utils/dataloader.py
learnkeyhole/utils/dataloader_medical.py
learnkeyhole/utils/utils.py
learnkeyhole/utils/utils_fit.py
learnkeyhole/utils/utils_metrics.py
learnkeyhole-0.1.3.dist-info/LICENSE
learnkeyhole-0.1.3.dist-info/METADATA
learnkeyhole-0.1.3.dist-info/WHEEL
learnkeyhole-0.1.3.dist-info/entry_points.txt
learnkeyhole-0.1.3.dist-info/top_level.txt
learnkeyhole-0.1.3.dist-info/zip-safe
learnkeyhole-0.1.3.dist-info/RECORD
